EmbeddingsDivision/__init__.py
EmbeddingsDivision/embeddings_division.py
embdiv-0.1.0.dist-info/LICENSE
embdiv-0.1.0.dist-info/METADATA
embdiv-0.1.0.dist-info/WHEEL
embdiv-0.1.0.dist-info/top_level.txt
embdiv-0.1.0.dist-info/RECORD
