Metadata-Version: 2.1
Name: embdiv
Version: 0.1.0
Summary: Library for dividing the Embedding layer of the LLM.
Home-page: https://github.com/1kkiRen/Embeddings-Division
Author: 1kkiren
Author-email: 1kkiren@mail.ru
Project-URL: GitHub, https://github.com/1kkiRen/Embeddings-Division
Keywords: embeddings division nlp
Classifier: Programming Language :: Python :: 3.10
Classifier: License :: OSI Approved :: Apache Software License
Classifier: Operating System :: OS Independent
Requires-Python: >=3.9
License-File: LICENSE
Requires-Dist: cachetools >=5.5.0
Requires-Dist: torch >=2.1.1
Requires-Dist: transformers >=4.45.2
